{
	"archive" : {},
	"artifacts" : 
	[
		{
			"path" : "elixor/libelixor.a"
		}
	],
	"backtrace" : 1,
	"backtraceGraph" : 
	{
		"commands" : 
		[
			"add_library",
			"include_directories"
		],
		"files" : 
		[
			"elixor/CMakeLists.txt",
			"CMakeLists.txt"
		],
		"nodes" : 
		[
			{
				"file" : 0
			},
			{
				"command" : 0,
				"file" : 0,
				"line" : 3,
				"parent" : 0
			},
			{
				"file" : 1
			},
			{
				"command" : 1,
				"file" : 1,
				"line" : 8,
				"parent" : 2
			}
		]
	},
	"compileGroups" : 
	[
		{
			"compileCommandFragments" : 
			[
				{
					"fragment" : "-g"
				},
				{
					"fragment" : "-std=gnu++2a"
				}
			],
			"includes" : 
			[
				{
					"backtrace" : 3,
					"path" : "/home/XFaon/CLionProjects/Elixor/includes"
				}
			],
			"language" : "CXX",
			"languageStandard" : 
			{
				"backtraces" : 
				[
					1
				],
				"standard" : "23"
			},
			"sourceIndexes" : 
			[
				0,
				1
			]
		}
	],
	"id" : "elixor::@dc3890e7cfe6d1cfd2c3",
	"name" : "elixor",
	"nameOnDisk" : "libelixor.a",
	"paths" : 
	{
		"build" : "elixor",
		"source" : "elixor"
	},
	"sourceGroups" : 
	[
		{
			"name" : "Source Files",
			"sourceIndexes" : 
			[
				0,
				1
			]
		}
	],
	"sources" : 
	[
		{
			"backtrace" : 1,
			"compileGroupIndex" : 0,
			"path" : "elixor/src/lexer/Lexer.cxx",
			"sourceGroupIndex" : 0
		},
		{
			"backtrace" : 1,
			"compileGroupIndex" : 0,
			"path" : "elixor/src/strings/Strings.cxx",
			"sourceGroupIndex" : 0
		}
	],
	"type" : "STATIC_LIBRARY"
}
